{
  "aws": [
    "aws/overview",
    {
      "Quick Start": [
        {
          "Install": [
            {
              "type": "autogenerated",
              "dirName": "aws/quick-start/install"
            }
          ]
        },
        "aws/quick-start/repositories"
      ],
      "Explore": [
        {
          "type": "autogenerated",
          "dirName": "aws/explore"
        }
      ],
      "Advanced": [
        {
          "type": "autogenerated",
          "dirName": "aws/advanced"
        }
      ]
    },
    "aws/deprovision",
    "aws/faq",
    "aws/credits"
  ],
  "civo": [
    "civo/overview",
    {
      "Quick Start": [
        {
          "Install": [
            {
              "type": "autogenerated",
              "dirName": "civo/quick-start/install"
            }
          ]
        },
        "civo/quick-start/repositories"
      ],
      "Explore": [
        {
          "type": "autogenerated",
          "dirName": "civo/explore"
        }
      ]
    },
    "civo/deprovision",
    "civo/faq",
    "civo/credits"
  ],
  "k3d": [
    "k3d/overview",
    {
      "Quick Start": [
        {
          "type": "autogenerated",
          "dirName": "k3d/quick-start"
        }
      ],
      "Explore": [
        {
          "type": "autogenerated",
          "dirName": "k3d/explore"
        }
      ]
    },
    "k3d/deprovision",
    "k3d/faq",
    "k3d/credits"
  ]
}
